MANIFEST.in
README.md
setup.py
olympus/__init__.py
olympus/eval_report.py
olympus/eval_report_test.py
olympus/eval_task.py
olympus/eval_task_test.py
olympus/model.py
olympus/model_test.py
olympus/utils.py
test_upload_v1.egg-info/PKG-INFO
test_upload_v1.egg-info/SOURCES.txt
test_upload_v1.egg-info/dependency_links.txt
test_upload_v1.egg-info/requires.txt
test_upload_v1.egg-info/top_level.txt